{"num_of_job": 5, "job_title": "Associate Systems Engineer", "country": "Greece", "city": "Athens", "job_description_link": "https://jobs.dell.com/job/athens/associate-systems-engineer/375/60983773248", "job_description": "NextGen\u202fPresales Academy\u202f- Associate Solutions Architect Athens, Greece At Dell Technologies, we are committed to creating innovative technologies that drive human progress. Our goal is to help our customers thrive in this constantly evolving digital world by delivering essential technology solutions to help move them forward. Powered by a workforce that values and celebrates different backgrounds, we create solutions that harness and amplify technology in the most meaningful ways. From hybrid cloud and high-performance computing to ambitious social impact and sustainability initiatives, what we do impacts everyone, everywhere. Join us as an Associate Solution Architect in our Presales team in Athens to do the best work of your career and make a profound social impact. What you\u2019ll achieve: The Dell Technologies NextGen Presales Academy is a 15 \u2013 30-month experiential training program designed to develop early-in-career & recent university graduates into skilled Presales Solutions Architects . The role of a Presales Solutions Architect blends the art of sales with the science of technology. We strive to act as trusted advisors to our customers to help recommend and design technology-based products and solutions. Following the program, participants will progress into a role as part of an industry leading presales organization where they will work with sales teams to help customers accomplish their IT initiatives and solve business challenges. You Will: Develop your knowledge of Dell Technologies\u2019 data center solutions Develop professional consultative skills used to gather customer requirements and IT environment specifics. Work with diverse teams and individuals to collaboratively architect\u202funique\u202fsolutions that drive customer innovation using cutting-edge technologies. Learn, practice & deliver presentations & demos to customers, highlighting product features, benefits & business value. Study the latest trends such as Cloud Computing, DevOps, Data Security and Artificial Intelligence which are changing how\u00a0customers deploy and operate IT infrastructure & applications. Take the first step towards your dream career Every Dell Technologies team member brings something unique to the table. Here\u2019s what we are looking for with this role: Essential Requirements Proven technology skills, outstanding interpersonal abilities, strong written and verbal communication skills. Attention to detail and problem-solving capabilities. Being an innovative thinker and a self-starter with a desire-to-win type mindset. Undergraduate Degree in a technical or business-related field.\u202f\u00a00-12 months after university graduation. Desirable Requirements Internship or work experience in technology-related field or a technology company. Who we are We believe that each of us has the power to make an impact. That\u2019s why we put our team members at the center of everything we do. If you\u2019re looking for an opportunity to grow your career with some of the best minds and most advanced tech in the industry, we\u2019re looking for you. Dell Technologies is a unique family of businesses that helps individuals and organizations transform how they work, live and play. Join us to build a future that works for everyone because Progress Takes All of Us. Application closing date: 26.02.2024 Dell Technologies is committed to the principle of equal employment opportunity for all employees and to providing employees with a work environment free of discrimination and harassment. Read the full Equal Employment Opportunity Policy here . Job ID: R240012 Dell\u2019s Flexible & Hybrid Work Culture At Dell Technologies, we believe our best work is done when flexibility is offered. We know that freedom and flexibility are crucial to all our employees no matter where you are located and our flexible and hybrid work style allows team members to have the freedom to ideate, be innovative, and drive results their way. To learn more about our work culture, please visit our locations page."}